README.md
setup.py
src/__init__.py
src/logic.py
src/main.py
testpypipackagehimanshubharti.egg-info/PKG-INFO
testpypipackagehimanshubharti.egg-info/SOURCES.txt
testpypipackagehimanshubharti.egg-info/dependency_links.txt
testpypipackagehimanshubharti.egg-info/entry_points.txt
testpypipackagehimanshubharti.egg-info/requires.txt
testpypipackagehimanshubharti.egg-info/top_level.txt