Metadata-Version: 2.1
Name: testpypipackagehimanshubharti
Version: 0.1.0
Summary: An application that informs you of the time in different locations and timezones
Home-page: https://www.youtube.com/channel/UCv9MUffHWyo2GgLIDLVu0KQ
Author: himanshu
Author-email: himanshu.hakerone@gmail.com
License: UNKNOWN
Platform: UNKNOWN
Classifier: Programming Language :: Python :: 3
Classifier: License :: OSI Approved :: MIT License
Classifier: Operating System :: OS Independent
